smsn_telegram_notify/__init__.py
smsn_telegram_notify/notify.py
smsn_telegram_notify-0.1.1.dist-info/licenses/LICENSE
smsn_telegram_notify-0.1.1.dist-info/METADATA
smsn_telegram_notify-0.1.1.dist-info/WHEEL
smsn_telegram_notify-0.1.1.dist-info/top_level.txt
smsn_telegram_notify-0.1.1.dist-info/RECORD
