Metadata-Version: 2.4
Name: smsn-telegram-notify
Version: 0.1.1
Summary: Simple helper for sending Telegram notifications
Author: Unknown
License: MIT License
Requires-Python: >=3.8
License-File: LICENSE
Requires-Dist: requests
Dynamic: license-file
